paretos/__init__.py
paretos/config.py
paretos/default_logger.py
paretos/exceptions.py
paretos/paretos.py
paretos/service_locator.py
paretos/version.py
paretos/athena/__init__.py
paretos/athena/athena_api_client.py
paretos/athena/athena_api_http_session.py
paretos/authentication/__init__.py
paretos/authentication/access_token.py
paretos/authentication/access_token_provider.py
paretos/authentication/authentication_error.py
paretos/authentication/keycloak_authenticator.py
paretos/authentication/keycloak_service.py
paretos/command/__init__.py
paretos/command/export_handler.py
paretos/command/obtain_handler.py
paretos/command/optimize_handler.py
paretos/command/predict_handler.py
paretos/command/use_case_handler.py
paretos/evaluation/__init__.py
paretos/evaluation/evaluation_planner.py
paretos/evaluation/evaluator.py
paretos/evaluation/kpi_sanitizer.py
paretos/evaluation/scheduler.py
paretos/evaluation/supervisor.py
paretos/export/__init__.py
paretos/export/evaluation_result.py
paretos/export/optimization_result.py
paretos/interface/__init__.py
paretos/interface/async_environment_interface.py
paretos/interface/design_parameter.py
paretos/interface/environment_interface.py
paretos/interface/evaluation_result_interface.py
paretos/interface/kpi_parameter.py
paretos/interface/optimization_problem.py
paretos/interface/optimization_result_interface.py
paretos/interface/parameter_value.py
paretos/interface/progress_interface.py
paretos/interface/run_terminator.py
paretos/interface/terminator_interface.py
paretos/optimization/__init__.py
paretos/optimization/default_terminator.py
paretos/optimization/evaluation.py
paretos/optimization/evaluations.py
paretos/optimization/optimization_problem.py
paretos/optimization/progress.py
paretos/optimization/project.py
paretos/optimization/design/__init__.py
paretos/optimization/design/design_parameter.py
paretos/optimization/design/design_space.py
paretos/optimization/design/design_values.py
paretos/optimization/design/designs.py
paretos-4.1.0.dist-info/LICENSE
paretos-4.1.0.dist-info/METADATA
paretos-4.1.0.dist-info/WHEEL
paretos-4.1.0.dist-info/top_level.txt
paretos-4.1.0.dist-info/RECORD
